kerasdeeplearning/__init__.py
kerasdeeplearning-0.1.dist-info/LICENSE.txt
kerasdeeplearning-0.1.dist-info/METADATA
kerasdeeplearning-0.1.dist-info/WHEEL
kerasdeeplearning-0.1.dist-info/top_level.txt
kerasdeeplearning-0.1.dist-info/RECORD
