Metadata-Version: 2.1
Name: kerasdeeplearning
Version: 0.1
Summary: keras for deep learning
Author: imad chougle
Author-email: imadchougle2@gmail.com
Classifier: Programming Language :: Python :: 3
Classifier: License :: OSI Approved :: MIT License
Classifier: Operating System :: OS Independent
License-File: LICENSE.txt
